[{"QuestionNo":"0","RedNumberofClicks":10,"BlueNumberofClicks":27},{"QuestionNo":"1","RedNumberofClicks":6,"BlueNumberofClicks":5},{"QuestionNo":"2","RedNumberofClicks":4,"BlueNumberofClicks":5},{"QuestionNo":"3","RedNumberofClicks":4,"BlueNumberofClicks":5},{"QuestionNo":"4","RedNumberofClicks":5,"BlueNumberofClicks":2},{"QuestionNo":"5","RedNumberofClicks":3,"BlueNumberofClicks":4},{"QuestionNo":"6","RedNumberofClicks":2,"BlueNumberofClicks":5},{"QuestionNo":"7","RedNumberofClicks":4,"BlueNumberofClicks":2},{"QuestionNo":"8","RedNumberofClicks":3,"BlueNumberofClicks":1},{"QuestionNo":"9","RedNumberofClicks":2,"BlueNumberofClicks":1},{"QuestionNo":"10","RedNumberofClicks":2,"BlueNumberofClicks":1},{"QuestionNo":"11","RedNumberofClicks":1,"BlueNumberofClicks":2},{"QuestionNo":"12","RedNumberofClicks":1,"BlueNumberofClicks":2},{"QuestionNo":"13","RedNumberofClicks":1,"BlueNumberofClicks":2},{"QuestionNo":"14","RedNumberofClicks":1,"BlueNumberofClicks":2},{"QuestionNo":"15","RedNumberofClicks":1,"BlueNumberofClicks":2},{"QuestionNo":"16","RedNumberofClicks":2,"BlueNumberofClicks":1},{"QuestionNo":"17","RedNumberofClicks":2,"BlueNumberofClicks":1},{"QuestionNo":"18","RedNumberofClicks":2,"BlueNumberofClicks":1},{"QuestionNo":"19","RedNumberofClicks":2,"BlueNumberofClicks":1},{"QuestionNo":"20","RedNumberofClicks":1,"BlueNumberofClicks":2},{"QuestionNo":"21","RedNumberofClicks":2,"BlueNumberofClicks":1},{"QuestionNo":"22","RedNumberofClicks":2,"BlueNumberofClicks":1},{"QuestionNo":"23","RedNumberofClicks":1,"BlueNumberofClicks":2},{"QuestionNo":"24","RedNumberofClicks":1,"BlueNumberofClicks":2},{"QuestionNo":"25","RedNumberofClicks":1,"BlueNumberofClicks":2},{"QuestionNo":"26","RedNumberofClicks":1,"BlueNumberofClicks":1},{"QuestionNo":"27","RedNumberofClicks":1,"BlueNumberofClicks":1},{"QuestionNo":"28","RedNumberofClicks":1,"BlueNumberofClicks":1},{"QuestionNo":"29","RedNumberofClicks":1,"BlueNumberofClicks":1}]